loglevel/__init__.py
loglevel-0.1.0.dist-info/DESCRIPTION.rst
loglevel-0.1.0.dist-info/METADATA
loglevel-0.1.0.dist-info/RECORD
loglevel-0.1.0.dist-info/WHEEL
loglevel-0.1.0.dist-info/metadata.json
loglevel-0.1.0.dist-info/top_level.txt
